clockDivSerial/clockDivMod.v
module clockDivMod (
  input [31:0] FREQ_VAL,   // 32-bit input
  input reset,
  input clk_in,            // 1-bit clock input
  output reg clk_out       // 1-bit clock output
);

  reg [31:0] counter = 0;          // 32-bit counter
  reg [31:0] freq_val;         // 32-bit storage for FREQ_VAL


  always @(posedge clk_in or posedge reset) begin
    if (reset) begin
          counter <= FREQ_VAL/2;
          clk_out <= 1'b0;
        end
        else begin
          if (counter == FREQ_VAL) begin
            counter <= 1'b0;
            clk_out <= ~clk_out;    // Toggle the output clock
          end else begin
            clk_out <= clk_out;  // explicit
            counter <= counter + 1;
        end
        end
  end

endmodule

clockDivSerial/ClockDivSerialTb.v
module ClockDivSerialTb;

  /* Make a reset that pulses once. */
  reg reset = 0;


  // One-bit output
  wire clk_out;
  
  // Frequency value for the clock divider
  reg [31:0] freq_val;

  initial begin
     $dumpfile("clockDivMod_test.vcd");
     $dumpvars(0,ClockDivSerialTb);
     // Initial frequency value
     freq_val = 4;

     # 17 reset = 1;
     # 100 reset = 1;
     # 100 freq_val = 9;
     
     # 29 reset = 1;
     # 5  reset = 0;
     
     # 513 $finish;
  end


  /* Make a regular pulsing clock. */
  reg clk = 0;
  always #1 clk = !clk;

     
  // Instance of clockDivMod
  clockDivMod clk_div_inst (
    .FREQ_VAL(freq_val),
    .reset(reset),
    .clk_in(clk),
    .clk_out(clk_out)
  );

  initial
     $monitor("At time %t, clk_out = %h (%0d)",
              $time, clk_out, clk_out);

endmodule

clockDivSerial/clockDivMod_test.vcd
$date
	Tue Sep  3 12:55:40 2024
$end
$version
	Icarus Verilog
$end
$timescale
	1s
$end
$scope module ClockDivSerialTb $end
$var wire 1 ! clk_out $end
$var reg 1 " clk $end
$var reg 32 # freq_val [31:0] $end
$var reg 1 $ reset $end
$scope module clk_div_inst $end
$var wire 32 % FREQ_VAL [31:0] $end
$var wire 1 " clk_in $end
$var wire 1 $ reset $end
$var reg 1 ! clk_out $end
$var reg 32 & counter [31:0] $end
$upscope $end
$upscope $end
$enddefinitions $end
$comment Show the parameter values. $end
$dumpall
$end
#0
$dumpvars
b0 &
b100 %
0$
b100 #
0"
x!
$end
#1
b1 &
1"
#2
0"
#3
b10 &
1"
#4
0"
#5
b11 &
1"
#6
0"
#7
b100 &
1"
#8
0"
#9
b0 &
1"
#10
0"
#11
b1 &
1"
#12
0"
#13
b10 &
1"
#14
0"
#15
b11 &
1"
#16
0"
#17
0!
b10 &
1"
1$
